aizen/__init__.py
aizen/function_definitions.json
aizen/generate_function_definitions.py
aizen/agents/__init__.py
aizen/agents/agentrunner.py
aizen/agents/configs/cryptoecho.agent.json
aizen/agents/configs/cryptopulse.agent.json
aizen/agents/configs/cryptotrader.agent.json
aizen/chains/__init__.py
aizen/chains/bsc.py
aizen/chains/solana.py
aizen/chains/utils/__init__.py
aizen/chains/utils/wallet.py
aizen/data/__init__.py
aizen/data/analytics/__init__.py
aizen/data/analytics/defillama.py
aizen/data/news/__init__.py
aizen/data/news/blockworks.py
aizen/data/news/theblock.py
aizen/data/vc_portfolio/__init__.py
aizen/data/vc_portfolio/base.py
aizen/data/vc_portfolio/binance_labs.py
aizen/data/vc_portfolio/dcg.py
aizen/data/vc_portfolio/multicoin.py
aizen/data/vc_portfolio/pantera.py
aizen/data/vc_portfolio/paradigm.py
aizen/protocols/__init__.py
aizen/protocols/pancakeswapv2.py
aizen/social/twitterclient.py
aizen_agents-0.1.0.dist-info/METADATA
aizen_agents-0.1.0.dist-info/WHEEL
aizen_agents-0.1.0.dist-info/licenses/LICENSE
aizen_agents-0.1.0.dist-info/RECORD
