Metadata-Version: 2.4
Name: aizen-agents
Version: 0.1.0
Summary: Web3 AI Agent Platform with powerful tools and realtime data
Project-URL: Homepage, https://github.com/redaicodes/aizen
Project-URL: Repository, https://github.com/redaicodes/aizen.git
Author-email: redaicodes <redaicodes@proton.me>
License: MIT License
License-File: LICENSE
Classifier: License :: OSI Approved :: MIT License
Classifier: Operating System :: OS Independent
Classifier: Programming Language :: Python :: 3
Requires-Python: >=3.9
Requires-Dist: aiohttp>=3.8.0
Requires-Dist: base58>=2.1.1
Requires-Dist: beautifulsoup4>=4.12.0
Requires-Dist: construct>=2.10.68
Requires-Dist: eth-account>=0.8.0
Requires-Dist: greenlet>=3.0.0
Requires-Dist: httpx>=0.26.0
Requires-Dist: lxml>=4.9.0
Requires-Dist: openai>=1.59.6
Requires-Dist: pandas>=2.0.0
Requires-Dist: playwright>=1.39.0
Requires-Dist: pydantic>=2.0.0
Requires-Dist: python-dotenv>=1.0.0
Requires-Dist: requests>=2.31.0
Requires-Dist: solana>=0.30.0
Requires-Dist: solders>=0.18.0
Requires-Dist: twikit>=0.2.0
Requires-Dist: typing-extensions>=4.8.0
Requires-Dist: web3>=7.6.1
Provides-Extra: dev
Requires-Dist: black>=23.0.0; extra == 'dev'
Requires-Dist: fontawesome-markdown>=0.2.6; extra == 'dev'
Requires-Dist: isort>=5.12.0; extra == 'dev'
Requires-Dist: mkdocs-material>=9.5.3; extra == 'dev'
Requires-Dist: mkdocs-mermaid2-plugin>=1.1.1; extra == 'dev'
Requires-Dist: mkdocs-minify-plugin>=0.7.1; extra == 'dev'
Requires-Dist: mkdocs-terminal>=4.7.0; extra == 'dev'
Requires-Dist: mkdocs>=1.6.1; extra == 'dev'
Requires-Dist: mkdocstrings>=0.27.0; extra == 'dev'
Requires-Dist: mkdocstrings[python]>=0.27.0; extra == 'dev'
Requires-Dist: mypy>=1.0.0; extra == 'dev'
Requires-Dist: pytest-asyncio>=0.21.0; extra == 'dev'
Requires-Dist: pytest>=7.0.0; extra == 'dev'
